yummycurry/__init__.py
yummycurry/curry.py
yummycurry-0.1.0.dist-info/LICENSE
yummycurry-0.1.0.dist-info/METADATA
yummycurry-0.1.0.dist-info/WHEEL
yummycurry-0.1.0.dist-info/top_level.txt
yummycurry-0.1.0.dist-info/RECORD
