Metadata-Version: 2.1
Name: yummycurry
Version: 0.1.0
Summary: Automatic currying, uncurrying and application of functions and methods
Home-page: https://github.com/Niriel/yummycurry
Author: Niriel
License: UNKNOWN
Keywords: curry currying uncurry uncurrying partial
Platform: UNKNOWN
Classifier: Development Status :: 3 - Alpha
Classifier: Intended Audience :: Developers
Classifier: Topic :: Software Development
Classifier: Topic :: Utilities
Classifier: License :: OSI Approved :: MIT License
Classifier: Programming Language :: Python :: 3.8
Requires-Python: >=3.8
Provides-Extra: test
Requires-Dist: pytest ; extra == 'test'
